ciphertrust/__init__.py
ciphertrust/_version.py
ciphertrust/api.py
ciphertrust/auth.py
ciphertrust/config.py
ciphertrust/exceptions.py
ciphertrust/models.py
ciphertrust/requestapi.py
ciphertrust/static.py
ciphertrust/utils.py
ciphertrust_sdk-1.0.17.dist-info/LICENSE
ciphertrust_sdk-1.0.17.dist-info/METADATA
ciphertrust_sdk-1.0.17.dist-info/WHEEL
ciphertrust_sdk-1.0.17.dist-info/top_level.txt
ciphertrust_sdk-1.0.17.dist-info/RECORD
