Metadata-Version: 2.1
Name: ciphertrust-sdk
Version: 1.0.17
Summary: Thales CipherTrust SDK RestAPI
Author-email: atav928 <dev@tavnets.com>
License: MIT License
Classifier: License :: OSI Approved :: MIT License
Classifier: Programming Language :: Python :: Implementation
Classifier: Programming Language :: Python :: 3.8
Classifier: Programming Language :: Python :: 3.9
Classifier: Programming Language :: Python :: 3.10
Requires-Python: <4,>=3.9
License-File: LICENSE
Requires-Dist: orjson ==3.8.*
Requires-Dist: PyJWT ==2.7.*
Requires-Dist: requests ~=2.28
Requires-Dist: dataclasses ==0.6
Requires-Dist: validators >=0.22.0
Requires-Dist: httpx ==0.24.*
Requires-Dist: PyYAML >=6.0
Requires-Dist: py-easy-logger >=0.0.5
Provides-Extra: test
Requires-Dist: pytest-cov ; extra == 'test'
Requires-Dist: pytest ; extra == 'test'
Requires-Dist: pytest-mock ; extra == 'test'
Requires-Dist: unittest2 ; extra == 'test'
Requires-Dist: dataclasses ; extra == 'test'
Requires-Dist: six ; extra == 'test'
